pier/__init__.py
pier/core.py
pier/tests/__init__.py
pier-0.1.2.dist-info/DESCRIPTION.rst
pier-0.1.2.dist-info/METADATA
pier-0.1.2.dist-info/metadata.json
pier-0.1.2.dist-info/pbr.json
pier-0.1.2.dist-info/RECORD
pier-0.1.2.dist-info/top_level.txt
pier-0.1.2.dist-info/WHEEL
