Metadata-Version: 2.0
Name: pier
Version: 0.1.2
Summary: A high-level Docker API
Home-page: https://github.com/Magnetic/Pier
Author: Magnetic Engineering
Author-email: engineering@magnetic.com
License: MIT
Platform: UNKNOWN
Classifier: Development Status :: 3 - Alpha
Classifier: License :: OSI Approved :: MIT License
Classifier: Operating System :: OS Independent
Classifier: Programming Language :: Python
Classifier: Programming Language :: Python :: 2.7
Classifier: Programming Language :: Python :: 2
Classifier: Programming Language :: Python :: Implementation :: CPython
Classifier: Programming Language :: Python :: Implementation :: PyPy
Requires-Dist: betterpath (>=0.2.2)
Requires-Dist: characteristic
Requires-Dist: docker-py (>=1.0.0)
